AUTHORS.rst
CHANGELOG.rst
MANIFEST.in
README.rst
setup.py
test_settings.py
django_maintenance_in_progress.egg-info/PKG-INFO
django_maintenance_in_progress.egg-info/SOURCES.txt
django_maintenance_in_progress.egg-info/dependency_links.txt
django_maintenance_in_progress.egg-info/not-zip-safe
django_maintenance_in_progress.egg-info/requires.txt
django_maintenance_in_progress.egg-info/top_level.txt
maintenance_in_progress/__init__.py
maintenance_in_progress/__init__.pyc
maintenance_in_progress/admin.py
maintenance_in_progress/admin.pyc
maintenance_in_progress/models.py
maintenance_in_progress/models.pyc
maintenance_in_progress/views.py
maintenance_in_progress/views.pyc
maintenance_in_progress/templates/maintenance_in_progress/500.html
maintenance_in_progress/tests/__init__.py
maintenance_in_progress/tests/__init__.pyc
maintenance_in_progress/tests/urls.py
maintenance_in_progress/tests/urls.pyc
maintenance_in_progress/tests/templates/error.html