Metadata-Version: 1.1
Name: django-maintenance-in-progress
Version: 0.1
Summary: Intercept possible 500 errors when site maintenance is in progress and display a friendly page.
Home-page: http://github.com/praekelt/django-maintenance-in-progress
Author: Hedley Roos
Author-email: hedleyroos@gmail.com
License: BSD
Platform: UNKNOWN
Classifier: Programming Language :: Python
Classifier: License :: OSI Approved :: BSD License
Classifier: Development Status :: 4 - Beta
Classifier: Operating System :: OS Independent
Classifier: Framework :: Django
Classifier: Intended Audience :: Developers
Classifier: Topic :: Internet :: WWW/HTTP :: Dynamic Content
